{
  "grades": [
    {
      "id": 5,
      "name": "Kyle Simpson",
      "course": "JavaScript",
      "grade": 100
    },
    {
      "id": 12,
      "name": "Brendan Eich",
      "course": "JavaScript",
      "grade": 100
    },
    {
      "id": 32,
      "name": "Douglas Crockford",
      "course": "JavaScript",
      "grade": 100
    },
    {
      "name": "Matt Chen",
      "course": "Web Development",
      "grade": 100,
      "id": 33
    },
    {
      "name": "Michael Lee",
      "course": "Web Development",
      "grade": "90",
      "id": 34
    },
    {
      "name": "Katherine Mcjagger",
      "course": "HTML",
      "grade": "100",
      "id": 35
    },
    {
      "name": "Kevin Lee",
      "course": "JavaScript",
      "grade": 95,
      "id": 36
    }
  ]
}